{
  "plugins": {
    "blink.cmp": {
      "rev": "b19413d214068f316c78978b08264ed1c41830ec",
      "src": "https://github.com/saghen/blink.cmp",
      "version": ">=0.0.0"
    },
    "conform.nvim": {
      "rev": "8314f4c9e205e7f30b62147069729f9a1227d8bf",
      "src": "https://github.com/stevearc/conform.nvim"
    },
    "indent-o-matic": {
      "rev": "764da1f30b5bb4a49035c3abc9a586322296b812",
      "src": "https://github.com/Darazaki/indent-o-matic"
    },
    "lazydev.nvim": {
      "rev": "5231c62aa83c2f8dc8e7ba957aa77098cda1257d",
      "src": "https://github.com/folke/lazydev.nvim"
    },
    "mini.nvim": {
      "rev": "43ec25063430196d36f5fff5758c9101775f3d57",
      "src": "https://github.com/nvim-mini/mini.nvim"
    },
    "nvim-bqf": {
      "rev": "ba2b365969d7c2c6301d48e13aeee59568765529",
      "src": "https://github.com/kevinhwang91/nvim-bqf"
    },
    "nvim-jdtls": {
      "rev": "f73731b543f5971e0da9665eb1d7ceffe1fde71f",
      "src": "https://github.com/mfussenegger/nvim-jdtls"
    },
    "nvim-lspconfig": {
      "rev": "41ceb6bba3a40128b7841f5b7f5a9dae7201e823",
      "src": "https://github.com/neovim/nvim-lspconfig"
    },
    "nvim-treesitter": {
      "rev": "c6dd314086f7b471bf6c9110092a94ce1c06d220",
      "src": "https://github.com/nvim-treesitter/nvim-treesitter"
    },
    "nvim-ts-autotag": {
      "rev": "c4ca798ab95b316a768d51eaaaee48f64a4a46bc",
      "src": "https://github.com/windwp/nvim-ts-autotag"
    },
    "oil.nvim": {
      "rev": "81b8a91735ad5cd24a6b3137f14a89f19176364f",
      "src": "https://github.com/stevearc/oil.nvim"
    },
    "quicker.nvim": {
      "rev": "771437c3e3672dba9233156e1c2e2fc1888a5fff",
      "src": "https://github.com/stevearc/quicker.nvim"
    },
    "tokyonight.nvim": {
      "rev": "5da1b76e64daf4c5d410f06bcb6b9cb640da7dfd",
      "src": "https://github.com/folke/tokyonight.nvim"
    },
    "vim-startuptime": {
      "rev": "b6f0d93f6b8cf6eee0b4c94450198ba2d6a05ff6",
      "src": "https://github.com/dstein64/vim-startuptime"
    }
  }
}